fhir_flex-2.0.0.dist-info/licenses/LICENSE
fhir_simple/__init__.py
fhir_simple/patient_mapping.py
fhir_flex-2.0.0.dist-info/METADATA
fhir_flex-2.0.0.dist-info/WHEEL
fhir_flex-2.0.0.dist-info/top_level.txt
fhir_flex-2.0.0.dist-info/RECORD
