Metadata-Version: 2.4
Name: fhir_flex
Version: 2.0.0
Summary: A flexible library to simplify and map FHIR Patient objects to custom JSON schemas.
Author: Bhushan Varade
Author-email: Bhushan Varade <bvarade02@gmail.com>
License: MIT
Keywords: fhir,patient,json,healthcare,flexible
Requires-Python: >=3.6
License-File: LICENSE
Dynamic: author
Dynamic: license-file
Dynamic: requires-python
